ISRpy/__init__.py
ISRpy/enoise.py
ISRpy/kmltools.py
ISRpy/pyigrf.py
ISRpy/beampack/ALTAIRbeam.py
ISRpy/beampack/AObeam.py
ISRpy/beampack/PFISRbeam.py
ISRpy/beampack/__init__.py
ISRpy/beampack/bahirdarbeam.py
ISRpy/beampack/beamtools.py
ISRpy/beampack/esrbeam.py
ISRpy/beampack/iris_evex_beam.py
ISRpy/beampack/irisbeam.py
ISRpy/beampack/jrobeam.py
ISRpy/beampack/jrobeam0.py
ISRpy/beampack/kairabeam.py
ISRpy/beampack/kwajbeam.py
ISRpy/beampack/laplatabeam.py
ISRpy/beampack/sanyabeam.py
ISRpy/beampack/tromsobeam.py
ISRpy/igrfdata/IGRFGEN7.DAT
ISRpy/igrfdata/IGRFGEN8.DAT
ISRpy/igrfdata/igrf10coeffs.txt
ISRpy/igrfdata/igrf11coeffs.txt
ISRpy/igrfdata/igrf12coeffs.txt
ISRpy/igrfdata/igrf13coeffs.txt
ISRpy/igrfdata/igrf14coeffs.txt
ISRpy/igrfdata/igrf9coeffs.txt
ISRpy/readpack/JROfileread.py
ISRpy/readpack/__init__.py
ISRpy/readpack/digital_rf_hdf5.py
ISRpy/readpack/irisread.py
ISRpy/readpack/jroread.py
ISRpy/readpack/rdvme.py
ISRpy-0.0.29.dist-info/LICENSE
ISRpy-0.0.29.dist-info/METADATA
ISRpy-0.0.29.dist-info/WHEEL
ISRpy-0.0.29.dist-info/top_level.txt
ISRpy-0.0.29.dist-info/RECORD
