Metadata-Version: 2.1
Name: ISRpy
Version: 0.0.29
Summary: Radar Tools
Home-page: https://github.com/radars-eceillinois/isrpy
Author: Erhan Kudeki
Author-email: erhan@illinois.edu
Classifier: Programming Language :: Python :: 3
Classifier: License :: OSI Approved :: MIT License
Classifier: Operating System :: OS Independent
Requires-Python: >=3.4
License-File: LICENSE
Requires-Dist: numpy
Requires-Dist: scipy
